docxtexthighlighter/__init__.py
docxtexthighlighter/text_highlighter.py
docxtexthighlighter-1.0.0.dist-info/licenses/LICENSE
docxtexthighlighter-1.0.0.dist-info/WHEEL
docxtexthighlighter-1.0.0.dist-info/METADATA
docxtexthighlighter-1.0.0.dist-info/RECORD
