Metadata-Version: 2.4
Name: docxtexthighlighter
Version: 1.0.0
Summary: A package that helps to highlight words in your docx file, and generate a new docx file with the highlighted words.
Author: mq
Author-email: mq <mq@example.com>
License-Expression: MIT
License-File: LICENSE
Classifier: Programming Language :: Python :: 3
Classifier: Programming Language :: Python :: 3.9
Classifier: Operating System :: OS Independent
Requires-Dist: lxml>=3.1.0
Requires-Dist: typing-extensions>=4.9.0
Requires-Dist: python-docx>=1.2.0
Requires-Python: >=3.9
Project-URL: Homepage, https://github.com/Weeerocks/Text-Highlighter
Project-URL: Issues, https://github.com/Weeerocks/Text-Highlighter/issues
